{
	"name": "DepartmentDatadataset",
	"properties": {
		"linkedServiceName": {
			"referenceName": "lsajay21demo_AzureBlobStorage1",
			"type": "LinkedServiceReference"
		},
		"annotations": [],
		"type": "DelimitedText",
		"typeProperties": {
			"location": {
				"type": "AzureBlobStorageLocation",
				"fileName": "dept.csv",
				"folderPath": "input",
				"container": "adfdemo"
			},
			"columnDelimiter": ",",
			"escapeChar": "\\",
			"firstRowAsHeader": true,
			"quoteChar": "\""
		},
		"schema": [
			{
				"name": "dept_id",
				"type": "String"
			},
			{
				"name": "dept_name",
				"type": "String"
			},
			{
				"name": "location",
				"type": "String"
			}
		]
	},
	"type": "Microsoft.DataFactory/factories/datasets"
}